timexus/__init__.py
timexus/_xsleep.py
timexus/cli.py
TimeXus-0.4.1.dist-info/METADATA
TimeXus-0.4.1.dist-info/WHEEL
TimeXus-0.4.1.dist-info/entry_points.txt
TimeXus-0.4.1.dist-info/top_level.txt
TimeXus-0.4.1.dist-info/RECORD
