Metadata-Version: 2.2
Name: TimeXus
Version: 0.4.1
Summary: TimeXus: Improved sleep(), flexible time units and system utilities.
Home-page: https://pypi.org/project/TimeXus/  # Keep the repository URL for now
Author: WolfDev
Author-email: ConexusDevs@email.com
Classifier: Programming Language :: Python :: 3
Classifier: License :: OSI Approved :: MIT License
Classifier: Operating System :: OS Independent
Requires-Python: >=3.6
Requires-Dist: Pillow>=9.0.0
Requires-Dist: pywin32>=303; sys_platform == "win32"
Requires-Dist: requests
Requires-Dist: pytz
Requires-Dist: psutil
Requires-Dist: qrcode
